README.txt
setup.py
fhkrems/__init__.py
fhkrems.portlet.youtubeplayer.egg-info/PKG-INFO
fhkrems.portlet.youtubeplayer.egg-info/SOURCES.txt
fhkrems.portlet.youtubeplayer.egg-info/dependency_links.txt
fhkrems.portlet.youtubeplayer.egg-info/entry_points.txt
fhkrems.portlet.youtubeplayer.egg-info/namespace_packages.txt
fhkrems.portlet.youtubeplayer.egg-info/not-zip-safe
fhkrems.portlet.youtubeplayer.egg-info/requires.txt
fhkrems.portlet.youtubeplayer.egg-info/top_level.txt
fhkrems/portlet/__init__.py
fhkrems/portlet/youtubeplayer/__init__.py
fhkrems/portlet/youtubeplayer/youtubeplayerportlet.py
fhkrems/portlet/youtubeplayer/browser/__init__.py
fhkrems/portlet/youtubeplayer/tests/__init__.py
fhkrems/portlet/youtubeplayer/tests/base.py
fhkrems/portlet/youtubeplayer/tests/test_portlet.py