Metadata-Version: 1.0
Name: fhkrems.portlet.youtubeplayer
Version: 1.0
Summary: Simple YouTube Player Portlet
Home-page: http://sandbox.fh-krems.ac.at/
Author: Michael Graf
Author-email: webmaster@fh-krems.ac.at
License: GPL
Keywords: plone,zope,portlet,fh krems,youtube
Platform: UNKNOWN
Classifier: Framework :: Plone
Classifier: Programming Language :: Python
